Workbook

Sheet Assumptions
A1: Assumptions & Rate Card
A3: Assumption | B3: Value | C3: Unit | D3: Notes / source
A4: RATE CARD (enter annual cost to company)
A5: Annual cost - developer/builder | B5: 3000000 | C5: INR/yr | D5: 30 LPA per user. Cost of the person who builds. | E5: loaded cost = ? CTC x what factor?
A6: Annual cost - business user / SME | B6: 4000000 | C6: INR/yr | D6: 40 LPA per user. Ops SME doing UAT, training, parallel run.
A7: Annual cost - governance/risk reviewer | B7: 6000000 | C7: INR/yr | D7: 60 LPA per user. AI governance, model risk, InfoSec reviewers.
A8: Working days per month | B8: 21 | C8: days | D8: Used to convert annual cost to daily rate.
A9: Working hours per day | B9: 8 | C9: hrs | D9: Used to convert daily rate to hourly rate.
A10: Derived daily rate - developer | B10: =B5/(12*B8) -> 11904.762 | C10: INR/day | D10: Annual cost / (12 x working days per month).
A11: Derived daily rate - SME | B11: =B6/(12*B8) -> 15873.016 | C11: INR/day | D11: Annual cost / (12 x working days per month).
A12: Derived daily rate - governance | B12: =B7/(12*B8) -> 23809.524 | C12: INR/day | D12: Annual cost / (12 x working days per month).
A13: Derived hourly rate - ops user (benefits) | B13: =B11/B9 -> 1984.127 | C13: INR/hr | D13: Assumed same band as SME; used to value hours saved.
A14: BENEFIT FACTORS
A15: Realisation factor (reference only) | B15: 0.7 | C15: % | D15: No longer used in formulas - Benefits & ROI now shows value of hours at 100% / 70% / 50% directly (editable there).
A16: Year-1 adoption factor | B16: 0.6 | C16: % | D16: Benefits don't start at 100% at go-live; year 1 typically achieves 50-70% as usage ramps. Years 2+ assumed 100%.
A17: OTHER FACTORS
A18: Annual fixes & enhancements factor (% of build+design cost) | B18: 0.2 | C18: % | D18: Norm 15-25% per year when actuals unknown.
A19: Evaluation horizon (years) | B19: 3 | C19: years | D19: Drives every 'N-year' label and calculation. | E19: 3yrs cost or more?
A21: LEGEND
A22: Blue text on yellow fill = input cell, edit these
A23: Black text = formula, do not overwrite
A24: Green text = pulls from another sheet

Sheet Cost Model
A1: Cost Model - AI Use Case | Example values shown
A3: ONE-TIME (BUILD PHASE) COSTS
A4: Cost item | B4: Effort (days) | C4: Rate basis | D4: Rate (INR/day) | E4: Cost (INR) | F4: Notes
A5: Analysis & design | B5: 5 | C5: Developer | D5: =Assumptions!$B$10 -> 11904.762 | E5: =B5*D5 -> 59523.81 | F5: Requirements, process mapping, solution design.
A6: Development / build | B6: 25 | C6: Developer | D6: =Assumptions!$B$10 -> 11904.762 | E6: =B6*D6 -> 297619.05 | F6: Core dev effort incl. prompt/eval iteration.
A7: Data preparation & access setup | B7: 3 | C7: Developer | D7: =Assumptions!$B$10 -> 11904.762 | E7: =B7*D7 -> 35714.286 | F7: Data cleanup, labeling, entitlements, API/folder access.
A8: Testing / UAT (business users) | B8: 6 | C8: SME | D8: =Assumptions!$B$11 -> 15873.016 | E8: =B8*D8 -> 95238.095 | F8: Ops users' testing time - often forgotten.
A9: Change management & training | B9: 3 | C9: SME | D9: =Assumptions!$B$11 -> 15873.016 | E9: =B9*D9 -> 47619.048 | F9: User training, SOP/procedure updates.
A10: Parallel run (old + new side by side) | B10: 4 | C10: SME | D10: =Assumptions!$B$11 -> 15873.016 | E10: =B10*D10 -> 63492.063 | F10: Double-running cost during cutover. Pure extra effort.
A11: Governance & validation | B11: 5 | C11: Governance | D11: =Assumptions!$B$12 -> 23809.524 | E11: =B11*D11 -> 119047.62 | F11: AI/model risk review, InfoSec, records mgmt, approvals.
A12: Dev & test: total AI requests/calls | B12: 3000 | C12: requests | F12: All AI calls across development iterations + testing.
A13: Dev & test: avg input tokens per request | B13: 2000 | C13: tokens
A14: Dev & test: avg output tokens per request | B14: 500 | C14: tokens
A15: Token / AI usage cost during dev & test | E15: =B12*(B13/1000000*B25+B14/1000000*B26) -> 3375 | F15: Requests x (input tokens x input price + output tokens x output price). Prices taken from the production price cells below.
A16: One-time purchases (tools, data licences, one-off fees) | E16: 0 | F16: One-off cash spend incl. any data licensing setup.
A17: TOTAL ONE-TIME COST | E17: =SUM(E5:E16) -> 721628.97
A19: ANNUAL MAINTENANCE COSTS (RECURRING, PER YEAR)
A20: Production token usage detail
A21: Item | B21: Value | C21: Unit | F21: Notes
A22: Requests / interactions per month | B22: =2500*30 -> 75000 | C22: req/mo | F22: How many times the AI is called in production per month.
A23: Avg input tokens per request | B23: 2000 | C23: tokens | F23: Prompt + context sent in.
A24: Avg output tokens per request | B24: 500 | C24: tokens | F24: Response generated.
A25: Price per 1M input tokens | B25: 250 | C25: INR | F25: From model provider price card. Placeholder.
A26: Price per 1M output tokens | B26: 1250 | C26: INR | F26: Output tokens usually cost 4-5x input. Placeholder.
A27: Monthly production token cost | B27: =B22*(B23/1000000*B25+B24/1000000*B26) -> 84375 | C27: INR/mo | F27: Requests x (input tokens x input price + output tokens x output price).
A28: Cost item | B28: Qty / basis | C28: Unit | D28: Unit cost (INR) | E28: Annual cost (INR) | F28: Notes
A29: Token / AI usage in production (from detail above) | E29: =B27*12 -> 1012500 | F29: Monthly token cost x 12. Add licence seats (e.g. Copilot) to Software licences below.
A30: Software licences, per year | E30: 0 | F30: Paid libraries/tools, AI licence seats, recurring data licences.
A31: Infrastructure, per year | E31: 60000 | F31: Server/VM or cloud compute; storage & database; networking; dev/UAT/prod environments; monitoring & logging; backup/DR; vector DB; API gateway. Nil if desktop-only.
A32: Fixes & enhancements (% of build+design cost) | D32: =Assumptions!$B$18 -> 0.2 | E32: =D32*(E5+E6) -> 71428.571 | F32: Bug fixes, small enhancements, model/prompt drift upkeep.
A33: Annual revalidation (governance re-review, attestation) | B33: 1 | C33: days/yr | D33: =Assumptions!$B$12 -> 23809.524 | E33: =B33*D33 -> 23809.524 | F33: Recurring governance cost of keeping an AI use case approved.
A34: TOTAL ANNUAL MAINTENANCE COST | E34: =SUM(E29:E33) -> 1167738.1
A35: Human oversight (maker-checker review of AI output) and rework are NOT costed here - they are deducted as hours on the Benefits & ROI sheet. Never count them in both places.
A37: COST SUMMARY
A38: Months live in Year 1 | B38: 12
A39: Year-1 cost (one-time + pro-rated annual maintenance) | E39: =E17+E34*B38/12 -> 1889367.1

Sheet Benefits & ROI
A1: Benefits & ROI
A3: STEP 1 - HOURS SAVED AND THEIR VALUE
A4: Task saved by AI | B4: Min/task | C4: Times/day | D4: Hrs/month | F4: Notes
A5: Task 1 (e.g. drafting client email responses) | B5: 15 | C5: 10 | D5: =B5*C5*Assumptions!$B$8/60 -> 52.5 | F5: Example: 15 min x 10/day x 21 days / 60 = 52.5 hrs.
A6: Task 2 (e.g. reconciliation break investigation) | B6: 10 | C6: 2 | D6: =B6*C6*Assumptions!$B$8/60 -> 7
A7: Task 3 | B7: 0 | C7: 0 | D7: =B7*C7*Assumptions!$B$8/60 -> 0 | F7: Add rows as needed; keep the subtotal range updated.
A8: Gross hours saved per month | D8: =SUM(D5:D7) -> 59.5
A9: Deductions | B9: Min/review | C9: Reviews/day | D9: Hrs/month | F9: Notes
A10: Less: human oversight / maker-checker review | B10: 3 | C10: 10 | D10: =B10*C10*Assumptions!$B$8/60 -> 10.5 | F10: Time a checker spends reviewing AI output before use.
A11: Less: exception handling / rework of wrong outputs | D11: 5 | F11: Hours/month fixing AI errors.
A12: NET HOURS SAVED PER MONTH | D12: =D8-D10-D11 -> 44
A13: Value of net hours saved (annual) - 100% realisation | D13: 1 | E13: =D12*12*Assumptions!$B$13*D13 -> 1047619 | F13: Net hours x 12 x ops hourly rate x realisation %. 100% = every freed hour productive; 70% = base case used in totals below; 50% = conservative.
A14: Value of net hours saved (annual) - 70% realisation | D14: 0.7 | E14: =D12*12*Assumptions!$B$13*D14 -> 733333.33
A15: Value of net hours saved (annual) - 50% realisation | D15: 0.5 | E15: =D12*12*Assumptions!$B$13*D15 -> 523809.52
A17: STEP 2 - CASH SAVINGS AND COST AVOIDANCE (ANNUAL)
A18: Item | E18: Annual (INR) | F18: Notes
A19: Cash savings - cancelled licences | E19: 0 | F19: Licences/subscriptions actually cancelled because of this use case.
A20: Cash savings - vendor fees avoided | E20: 0 | F20: Outsourced work / vendor charges that stop.
A21: Cash savings - overtime eliminated | E21: 0 | F21: Paid overtime that stops.
A22: Total cash savings | E22: =SUM(E19:E21) -> 0
A23: Cost avoidance | E23: 0 | F23: Hiring avoided as volumes grow; penalties/claims the firm has actually paid historically x expected reduction (e.g. settlement-fail penalties, interest claims).
A24: TOTAL ANNUAL BENEFIT (full adoption) | E24: =E14+E22+E23 -> 733333.33 | F24: Uses the 70% realisation row as base case. Swap E14 for E13/E15 to see the 100%/50% scenario.
A25: Year-1 benefit (x Year-1 adoption factor) | E25: =E24*Assumptions!$B$16 -> 440000 | F25: Usage may not be 100% in year1
A27: STEP 3 - ROI METRICS
A28: Total one-time cost | E28: ='Cost Model'!E17 -> 721628.97
A29: Total annual maintenance cost | E29: ='Cost Model'!E34 -> 1167738.1
A30: Annual net benefit (excl. one-time cost ) | E30: =E24-E29 -> -434404.76
A31: Payback period (months) | E31: =IF(E30<=0,"Never recovered",E28/E30*12) -> Never recovered | F31: One-time cost / annual net benefit x 12 = months until the build investment is recovered.
